canesm_process-2025.9.1.dist-info/licenses/LICENSE
canproc/__init__.py
canproc/cli/__init__.py
canproc/dag/__init__.py
canproc/dag/dag.py
canproc/dag/utils.py
canproc/pipelines/__init__.py
canproc/pipelines/loaders.py
canproc/pipelines/pipelines.py
canproc/pipelines/utils.py
canproc/pipelines/variable.py
canproc/processors/__init__.py
canproc/processors/base.py
canproc/processors/interpolate.py
canproc/processors/physics.py
canproc/processors/xarray_ops.py
canproc/runners/__init__.py
canproc/runners/dask.py
canproc/runners/distributed.py
canproc/templates/pipelines/canesm_pipeline.yaml
canproc/templates/pipelines/canesm_pipeline_v52.yaml
canproc/templates/pipelines/cmip/core/core.yaml
canproc/templates/pipelines/cmip/core/atmosphere/precipitation.yaml
canproc/templates/pipelines/cmip/core/atmosphere/radiation.yaml
canproc/templates/pipelines/cmip/core/atmosphere/temperature.yaml
canproc/templates/pipelines/cmip/volmip/volmip.yaml
canproc/templates/pipelines/custom/rlr001/pam.yaml
canproc/templates/pipelines/custom/rlr001/variability.yaml
canproc/templates/pipelines/rtd/core.yaml
canesm_process-2025.9.1.dist-info/METADATA
canesm_process-2025.9.1.dist-info/WHEEL
canesm_process-2025.9.1.dist-info/entry_points.txt
canesm_process-2025.9.1.dist-info/top_level.txt
canesm_process-2025.9.1.dist-info/RECORD
