Metadata-Version: 2.4
Name: canesm-process
Version: 2025.9.1
Summary: CanESM data pipeline tools
Author-email: Landon Rieger <landon.rieger@ec.gc.ca>
License: MIT License
Requires-Python: >=3.10
License-File: LICENSE
Requires-Dist: pydantic>=2.0
Requires-Dist: numpy
Requires-Dist: xarray>=2024.01.0
Requires-Dist: click
Requires-Dist: dask
Requires-Dist: scipy
Requires-Dist: numba
Provides-Extra: test
Requires-Dist: pytest; extra == "test"
Requires-Dist: pytest-cov; extra == "test"
Provides-Extra: lint
Requires-Dist: black; extra == "lint"
Provides-Extra: ccc
Requires-Dist: fstd2nc; extra == "ccc"
Provides-Extra: vis
Requires-Dist: graphviz; extra == "vis"
Requires-Dist: python-graphviz; extra == "vis"
Provides-Extra: docs
Requires-Dist: sphinx; extra == "docs"
Requires-Dist: sphinxcontrib-mermaid; extra == "docs"
Requires-Dist: sphinx-book-theme; extra == "docs"
Requires-Dist: sphinx-design; extra == "docs"
Requires-Dist: sphinx-tabs; extra == "docs"
Provides-Extra: dev
Requires-Dist: canesm-process[docs,lint,test]; extra == "dev"
Dynamic: license-file
